LICENSE
MANIFEST.in
README.rst
setup.py
oe_sphinx_theme/__init__.py
oe_sphinx_theme.egg-info/PKG-INFO
oe_sphinx_theme.egg-info/SOURCES.txt
oe_sphinx_theme.egg-info/dependency_links.txt
oe_sphinx_theme.egg-info/not-zip-safe
oe_sphinx_theme.egg-info/requires.txt
oe_sphinx_theme.egg-info/top_level.txt
oe_sphinx_theme/theme/oe_sphinx/globaltoc.html
oe_sphinx_theme/theme/oe_sphinx/index-sidebar.html
oe_sphinx_theme/theme/oe_sphinx/layout.html
oe_sphinx_theme/theme/oe_sphinx/localtoc.html
oe_sphinx_theme/theme/oe_sphinx/relations.html
oe_sphinx_theme/theme/oe_sphinx/search.html
oe_sphinx_theme/theme/oe_sphinx/searchbox.html
oe_sphinx_theme/theme/oe_sphinx/theme.conf
oe_sphinx_theme/theme/oe_sphinx/static/Gemfile
oe_sphinx_theme/theme/oe_sphinx/static/bower.json
oe_sphinx_theme/theme/oe_sphinx/static/config.rb
oe_sphinx_theme/theme/oe_sphinx/static/favicon.ico
oe_sphinx_theme/theme/oe_sphinx/static/robots.txt
oe_sphinx_theme/theme/oe_sphinx/static/.sass-cache/1b2288cc0d999e96ca517128294dded1449d5926/foundation.scssc
oe_sphinx_theme/theme/oe_sphinx/static/.sass-cache/2882bfd36f6d99d1c2d11b409b975713109c4d90/_functions.scssc
oe_sphinx_theme/theme/oe_sphinx/static/.sass-cache/3ef7dff7812d5345439142ebb2638804ca80375e/app.scssc
oe_sphinx_theme/theme/oe_sphinx/static/.sass-cache/5a50cf82a24e3b5f16e62d67befedac97917bbd2/_accordion.scssc
oe_sphinx_theme/theme/oe_sphinx/static/.sass-cache/5a50cf82a24e3b5f16e62d67befedac97917bbd2/_alert-boxes.scssc
oe_sphinx_theme/theme/oe_sphinx/static/.sass-cache/5a50cf82a24e3b5f16e62d67befedac97917bbd2/_block-grid.scssc
oe_sphinx_theme/theme/oe_sphinx/static/.sass-cache/5a50cf82a24e3b5f16e62d67befedac97917bbd2/_breadcrumbs.scssc
oe_sphinx_theme/theme/oe_sphinx/static/.sass-cache/5a50cf82a24e3b5f16e62d67befedac97917bbd2/_button-groups.scssc
oe_sphinx_theme/theme/oe_sphinx/static/.sass-cache/5a50cf82a24e3b5f16e62d67befedac97917bbd2/_buttons.scssc
oe_sphinx_theme/theme/oe_sphinx/static/.sass-cache/5a50cf82a24e3b5f16e62d67befedac97917bbd2/_clearing.scssc
oe_sphinx_theme/theme/oe_sphinx/static/.sass-cache/5a50cf82a24e3b5f16e62d67befedac97917bbd2/_dropdown-buttons.scssc
oe_sphinx_theme/theme/oe_sphinx/static/.sass-cache/5a50cf82a24e3b5f16e62d67befedac97917bbd2/_dropdown.scssc
