Metadata-Version: 1.1
Name: oe-sphinx-theme
Version: 0.4.0
Summary: OE sphinx theme
Home-page: http://www.onroerenderfgoed.be/
Author: OE Sphinx
Author-email: klaas.millet@rwo.vlaanderen.be
License: BSD
Platform: UNKNOWN
Classifier: License :: OSI Approved :: BSD License
Classifier: Programming Language :: Python
Classifier: Programming Language :: Python :: 2.6
Classifier: Programming Language :: Python :: 2.7
Classifier: Development Status :: 4 - Beta
Classifier: Operating System :: OS Independent
